coaclient/__init__.py
coaclient/constants.py
coaclient/log.py
coaclient/main.py
coaclient/version.py
coaclient/cli/__init__.py
coaclient/cli/args.py
coaclient/cli/cli.py
coaclient/cli/formatters.py
coaclient/cli/parsers.py
coaclient/commands/__init__.py
coaclient/commands/config.py
coaclient/commands/version.py
coaclient/exceptions/__init__.py
coaclient/exceptions/base.py
coaclient/exceptions/commands.py
coaclient/exceptions/oauth2.py
coaclient/oauth2/__init__.py
coaclient/oauth2/client.py
coaclient/oauth2/config.py
coaclient/oauth2/settings.py
coaclient/oauth2/utils.py
coaclient-1.2.0.dist-info/METADATA
coaclient-1.2.0.dist-info/WHEEL
coaclient-1.2.0.dist-info/entry_points.txt
coaclient-1.2.0.dist-info/top_level.txt
coaclient-1.2.0.dist-info/RECORD
