Metadata-Version: 2.1
Name: coaclient
Version: 1.2.0
Summary: OAuth2.0 client for the Coursera App Platform.
Home-page: https://github.com/blittlemore-coursera/coaclient/
Author: Ievgen Arbuznykov, Anton Makrushyn
Author-email: xxxantikvarxxx@gmail.com, ansermak@gmail.com
License: Apache
Keywords: coursera sdk cli tool oauth2
Platform: UNKNOWN
Classifier: Development Status :: 5 - Production/Stable
Classifier: License :: OSI Approved :: Apache Software License
Classifier: Programming Language :: Python :: 3
Requires-Python: >=3.7
Requires-Dist: requests (>=2.23.0)
Requires-Dist: semver (>=2.9.0)
Requires-Dist: python-status (==1.0.1)
